odoo/addons/stock_move_auto_assign_auto_release/README.rst
odoo/addons/stock_move_auto_assign_auto_release/__init__.py
odoo/addons/stock_move_auto_assign_auto_release/__manifest__.py
odoo/addons/stock_move_auto_assign_auto_release/data/queue_job_channel_data.xml
odoo/addons/stock_move_auto_assign_auto_release/data/queue_job_function_data.xml
odoo/addons/stock_move_auto_assign_auto_release/i18n/it.po
odoo/addons/stock_move_auto_assign_auto_release/i18n/stock_move_auto_assign_auto_release.pot
odoo/addons/stock_move_auto_assign_auto_release/models/__init__.py
odoo/addons/stock_move_auto_assign_auto_release/models/product_product.py
odoo/addons/stock_move_auto_assign_auto_release/models/stock_move.py
odoo/addons/stock_move_auto_assign_auto_release/models/stock_picking.py
odoo/addons/stock_move_auto_assign_auto_release/readme/CONTRIBUTORS.md
odoo/addons/stock_move_auto_assign_auto_release/readme/CREDITS.md
odoo/addons/stock_move_auto_assign_auto_release/readme/DESCRIPTION.md
odoo/addons/stock_move_auto_assign_auto_release/static/description/icon.png
odoo/addons/stock_move_auto_assign_auto_release/static/description/index.html
odoo/addons/stock_move_auto_assign_auto_release/tests/__init__.py
odoo/addons/stock_move_auto_assign_auto_release/tests/test_assign_auto_release.py
odoo_addon_stock_move_auto_assign_auto_release-18.0.1.0.1.dist-info/METADATA
odoo_addon_stock_move_auto_assign_auto_release-18.0.1.0.1.dist-info/WHEEL
odoo_addon_stock_move_auto_assign_auto_release-18.0.1.0.1.dist-info/top_level.txt
odoo_addon_stock_move_auto_assign_auto_release-18.0.1.0.1.dist-info/RECORD
