Metadata-Version: 2.1
Name: odoo-addon-stock_move_auto_assign_auto_release
Version: 18.0.1.0.1
Requires-Python: >=3.10
Requires-Dist: odoo-addon-stock_available_to_promise_release==18.0.*
Requires-Dist: odoo-addon-stock_move_auto_assign==18.0.*
Requires-Dist: odoo==18.0.*
Summary: Auto release moves after auto assign
Home-page: https://github.com/OCA/stock-logistics-workflow
License: AGPL-3
Author: ACSONE SA/NV,Odoo Community Association (OCA)
Author-email: support@odoo-community.org
Classifier: Programming Language :: Python
Classifier: Framework :: Odoo
Classifier: Framework :: Odoo :: 18.0
Classifier: License :: OSI Approved :: GNU Affero General Public License v3
